msoffice_decrypt.py
msoffice_decrypt-1.0.1.dist-info/DESCRIPTION.rst
msoffice_decrypt-1.0.1.dist-info/METADATA
msoffice_decrypt-1.0.1.dist-info/RECORD
msoffice_decrypt-1.0.1.dist-info/WHEEL
msoffice_decrypt-1.0.1.dist-info/entry_points.txt
msoffice_decrypt-1.0.1.dist-info/metadata.json
msoffice_decrypt-1.0.1.dist-info/top_level.txt
