Metadata-Version: 2.0
Name: msoffice-decrypt
Version: 1.0.1
Summary: Python tool and library for decrypting encrypted MS Office files with a password
Home-page: https://github.com/unixfreak0037/msoffice_decrypt
Author: John Davison
Author-email: UNKNOWN
License: MIT
Keywords: Microsoft Office,decryption,passwords
Platform: UNKNOWN
Classifier: Development Status :: 5 - Production/Stable
Classifier: Intended Audience :: Developers
Classifier: Intended Audience :: Information Technology
Classifier: Operating System :: OS Independent
Classifier: License :: OSI Approved :: MIT License
Classifier: Programming Language :: Python :: 3 :: Only
Classifier: Programming Language :: Python :: 3
Classifier: Programming Language :: Python :: 3.0
Classifier: Programming Language :: Python :: 3.1
Classifier: Programming Language :: Python :: 3.2
Classifier: Programming Language :: Python :: 3.3
Classifier: Programming Language :: Python :: 3.4
Classifier: Programming Language :: Python :: 3.5
Classifier: Programming Language :: Python :: 3.6
Requires-Dist: olefile
Requires-Dist: pycrypto
